smash/__init__.py
smash/__main__.py
smash/boot/__init__.py
smash/boot/__main__.py
smash/boot/archive.py
smash/boot/context_menus.py
smash/boot/strap.py
smash/core/config.py
smash/core/constants.py
smash/core/env.py
smash/core/exporter.py
smash/core/handler.py
smash/core/instance.py
smash/core/pkg.py
smash/core/platform.py
smash/core/plugins.py
smash/core/tool.py
smash/core/user.py
smash/core/yamlisp.py
smash/dash/__init__.py
smash/dash/__main__.py
smash/env/__init__.py
smash/env/__main__.py
smash/pkg/__init__.py
smash/pkg/__main__.py
smash/setup/arguments.py
smash/templates/__init__.py
smash/templates/__stop__
smash/templates/smash.py
smash/templates/smash.spec
smash/templates/__pycache__/__init__.cpython-36.pyc
smash/templates/host/__mac__.yml
smash/templates/host/__nix__.yml
smash/templates/host/__pkg__.yml
smash/templates/host/__win__.yml
smash/templates/instance/__env__.yml
smash/templates/instance/__pkg__.yml
smash/templates/instance/__root__.yml
smash/templates/net/__pkg__.yml
smash/templates/python/__pkg__.yml
smash/test/__init__.py
smash/test/__main__.py
smash/test/dummy.py
smash/tool/__init__.py
smash/tool/download_monitor.py
smash/tool/log_monitor.py
smash/tool/master.py
smash/tool/notify.py
smash/tool/repo.py
smash/util/__init__.py
smash/util/meta.py
smash/util/out.py
smash/util/path.py
smash/util/proc.py
smash/util/xml.py
smash/util/yaml.py
smash-0.0.3.dist-info/DESCRIPTION.rst
smash-0.0.3.dist-info/METADATA
smash-0.0.3.dist-info/RECORD
smash-0.0.3.dist-info/WHEEL
smash-0.0.3.dist-info/entry_points.txt
smash-0.0.3.dist-info/metadata.json
smash-0.0.3.dist-info/top_level.txt
smash-0.0.3.dist-info/zip-safe
