Metadata-Version: 2.0
Name: smash
Version: 0.0.3
Summary: --- Smart Shell
Requires-Dist: click
Requires-Dist: colorama
Requires-Dist: colored-traceback
Requires-Dist: conda
Requires-Dist: cookiecutter
Requires-Dist: dulwich
Requires-Dist: ordered-set
Requires-Dist: powertools
Requires-Dist: psutil
Requires-Dist: ruamel.yaml
Requires-Dist: termcolor
Requires-Dist: wget
Requires-Dist: xmltodict
